Tokenkeycloak/__init__.py
Tokenkeycloak/connection.py
Tokenkeycloak/error.py
Tokenkeycloak/property_token.py
Tokenkeycloak/version.py
robotframework_tokenkeycloak-0.0.2.dist-info/LICENSE
robotframework_tokenkeycloak-0.0.2.dist-info/METADATA
robotframework_tokenkeycloak-0.0.2.dist-info/WHEEL
robotframework_tokenkeycloak-0.0.2.dist-info/top_level.txt
robotframework_tokenkeycloak-0.0.2.dist-info/RECORD
